{
  "data": {
    "article": {},
    "attachments": {},
    "author_id": "2057425772198215680",
    "conversation_id": "2067098834090758348",
    "created_at": "2026-06-17T06:04:58.000Z",
    "edit_controls": {
      "editable_until": "2026-06-17T07:04:58.000Z",
      "edits_remaining": 5,
      "is_edit_eligible": false
    },
    "edit_history_tweet_ids": [
      "2067126337509486607"
    ],
    "entities": {
      "mentions": [
        {
          "end": 15,
          "id": "2056401506791026689",
          "start": 0,
          "username": "entivv14xiRcrd"
        }
      ]
    },
    "geo": {},
    "id": "2067126337509486607",
    "in_reply_to_user_id": "2056401506791026689",
    "lang": "qme",
    "note_tweet": {
      "entities": {}
    },
    "possibly_sensitive": false,
    "public_metrics": {
      "bookmark_count": 0,
      "impression_count": 0,
      "like_count": 0,
      "quote_count": 0,
      "reply_count": 0,
      "retweet_count": 0
    },
    "referenced_tweets": [
      {
        "id": "2067125752685101515",
        "type": "replied_to"
      }
    ],
    "reply_settings": "everyone",
    "text": "@entivv14xiRcrd 🤏🤏🤏"
  },
  "includes": {
    "tweets": [
      {
        "article": {},
        "attachments": {},
        "author_id": "2057425772198215680",
        "conversation_id": "2067098834090758348",
        "created_at": "2026-06-17T06:04:58.000Z",
        "edit_controls": {
          "editable_until": "2026-06-17T07:04:58.000Z",
          "edits_remaining": 5,
          "is_edit_eligible": false
        },
        "edit_history_tweet_ids": [
          "2067126337509486607"
        ],
        "entities": {
          "mentions": [
            {
              "end": 15,
              "id": "2056401506791026689",
              "start": 0,
              "username": "entivv14xiRcrd"
            }
          ]
        },
        "geo": {},
        "id": "2067126337509486607",
        "in_reply_to_user_id": "2056401506791026689",
        "lang": "qme",
        "note_tweet": {
          "entities": {}
        },
        "possibly_sensitive": false,
        "public_metrics": {
          "bookmark_count": 0,
          "impression_count": 0,
          "like_count": 0,
          "quote_count": 0,
          "reply_count": 0,
          "retweet_count": 0
        },
        "referenced_tweets": [
          {
            "id": "2067125752685101515",
            "type": "replied_to"
          }
        ],
        "reply_settings": "everyone",
        "text": "@entivv14xiRcrd 🤏🤏🤏"
      },
      {
        "article": {},
        "attachments": {},
        "author_id": "2056401506791026689",
        "conversation_id": "2067098834090758348",
        "created_at": "2026-06-17T06:02:39.000Z",
        "edit_controls": {
          "editable_until": "2026-06-17T07:02:39.000Z",
          "edits_remaining": 5,
          "is_edit_eligible": false
        },
        "edit_history_tweet_ids": [
          "2067125752685101515"
        ],
        "entities": {
          "mentions": [
            {
              "end": 11,
              "id": "2057425772198215680",
              "start": 0,
              "username": "boqiaoahm4"
            }
          ]
        },
        "geo": {},
        "id": "2067125752685101515",
        "in_reply_to_user_id": "2057425772198215680",
        "lang": "ja",
        "note_tweet": {
          "entities": {}
        },
        "possibly_sensitive": false,
        "public_metrics": {
          "bookmark_count": 0,
          "impression_count": 4,
          "like_count": 1,
          "quote_count": 0,
          "reply_count": 1,
          "retweet_count": 0
        },
        "referenced_tweets": [
          {
            "id": "2067125330192851403",
            "type": "replied_to"
          }
        ],
        "reply_settings": "everyone",
        "text": "@boqiaoahm4 我想和玉玉结婚🥰"
      }
    ],
    "users": [
      {
        "created_at": "2026-05-21T11:38:55.000Z",
        "description": "薄巧/炸玉 \n防炸@okokok333444\n查成分回fo\nod自伤精神病傻逼贱货婊子畜生一枚",
        "entities": {
          "description": {
            "mentions": [
              {
                "end": 22,
                "start": 9,
                "username": "okokok333444"
              }
            ]
          },
          "url": {
            "urls": [
              {
                "display_url": "ngl.link/boboboqiao",
                "end": 23,
                "expanded_url": "https://ngl.link/boboboqiao",
                "start": 0,
                "url": "https://t.co/Al4Mvhwm7Y"
              }
            ]
          }
        },
        "id": "2057425772198215680",
        "name": "炸玉/二代目",
        "profile_image_url": "https://pbs.twimg.com/profile_images/2057427270990770176/9ouSJRp6_normal.jpg",
        "protected": false,
        "public_metrics": {
          "followers_count": 644,
          "following_count": 380,
          "like_count": 2011,
          "listed_count": 0,
          "media_count": 62,
          "tweet_count": 1111
        },
        "url": "https://t.co/Al4Mvhwm7Y",
        "username": "boqiaoahm4",
        "verified": false
      },
      {
        "created_at": "2026-05-18T15:49:48.000Z",
        "description": "我喜欢温柔的人\n🐼我喜欢熊猫\nhttps://t.co/xm6SjMmQ1w",
        "entities": {
          "description": {
            "urls": [
              {
                "display_url": "ngl.link/entivv14xirxrd",
                "end": 38,
                "expanded_url": "https://ngl.link/entivv14xirxrd",
                "start": 15,
                "url": "https://t.co/xm6SjMmQ1w"
              }
            ]
          }
        },
        "id": "2056401506791026689",
        "name": "なみだ",
        "pinned_tweet_id": "2067093206500884952",
        "profile_image_url": "https://pbs.twimg.com/profile_images/2066851577319825408/pJaaRkGl_normal.jpg",
        "protected": false,
        "public_metrics": {
          "followers_count": 25,
          "following_count": 39,
          "like_count": 98,
          "listed_count": 0,
          "media_count": 22,
          "tweet_count": 171
        },
        "username": "entivv14xiRcrd",
        "verified": false
      }
    ]
  }
}