{
  "data": {
    "article": {},
    "attachments": {
      "media_keys": [
        "3_2068911963481272320"
      ],
      "media_source_tweet_id": [
        "2068911969076412605"
      ]
    },
    "author_id": "2057425772198215680",
    "conversation_id": "2068977145104540101",
    "created_at": "2026-06-22T08:39:25.000Z",
    "edit_controls": {
      "editable_until": "2026-06-22T09:39:25.000Z",
      "edits_remaining": 5,
      "is_edit_eligible": false
    },
    "edit_history_tweet_ids": [
      "2068977145104540101"
    ],
    "entities": {
      "mentions": [
        {
          "end": 19,
          "id": "2047894021457211393",
          "start": 3,
          "username": "FanQie_QianQian"
        }
      ],
      "urls": [
        {
          "display_url": "pic.x.com/luDeWwJr6v",
          "end": 44,
          "expanded_url": "https://x.com/FanQie_QianQian/status/2068911969076412605/photo/1",
          "media_key": "3_2068911963481272320",
          "start": 21,
          "url": "https://t.co/luDeWwJr6v"
        }
      ]
    },
    "geo": {},
    "id": "2068977145104540101",
    "lang": "zxx",
    "note_tweet": {
      "entities": {}
    },
    "possibly_sensitive": true,
    "public_metrics": {
      "bookmark_count": 0,
      "impression_count": 0,
      "like_count": 0,
      "quote_count": 0,
      "reply_count": 0,
      "retweet_count": 0
    },
    "referenced_tweets": [
      {
        "id": "2068911969076412605",
        "type": "retweeted"
      }
    ],
    "reply_settings": "everyone",
    "text": "RT @FanQie_QianQian: https://t.co/luDeWwJr6v"
  },
  "includes": {
    "media": [
      {
        "height": 894,
        "media_key": "3_2068911963481272320",
        "public_metrics": {},
        "type": "photo",
        "url": "https://pbs.twimg.com/media/HLZAeB7bcAAWYHx.jpg",
        "width": 1096
      }
    ],
    "tweets": [
      {
        "article": {},
        "attachments": {
          "media_keys": [
            "3_2068911963481272320"
          ],
          "media_source_tweet_id": [
            "2068911969076412605"
          ]
        },
        "author_id": "2057425772198215680",
        "conversation_id": "2068977145104540101",
        "created_at": "2026-06-22T08:39:25.000Z",
        "edit_controls": {
          "editable_until": "2026-06-22T09:39:25.000Z",
          "edits_remaining": 5,
          "is_edit_eligible": false
        },
        "edit_history_tweet_ids": [
          "2068977145104540101"
        ],
        "entities": {
          "mentions": [
            {
              "end": 19,
              "id": "2047894021457211393",
              "start": 3,
              "username": "FanQie_QianQian"
            }
          ],
          "urls": [
            {
              "display_url": "pic.x.com/luDeWwJr6v",
              "end": 44,
              "expanded_url": "https://x.com/FanQie_QianQian/status/2068911969076412605/photo/1",
              "media_key": "3_2068911963481272320",
              "start": 21,
              "url": "https://t.co/luDeWwJr6v"
            }
          ]
        },
        "geo": {},
        "id": "2068977145104540101",
        "lang": "zxx",
        "note_tweet": {
          "entities": {}
        },
        "possibly_sensitive": true,
        "public_metrics": {
          "bookmark_count": 0,
          "impression_count": 0,
          "like_count": 0,
          "quote_count": 0,
          "reply_count": 0,
          "retweet_count": 0
        },
        "referenced_tweets": [
          {
            "id": "2068911969076412605",
            "type": "retweeted"
          }
        ],
        "reply_settings": "everyone",
        "text": "RT @FanQie_QianQian: https://t.co/luDeWwJr6v"
      },
      {
        "article": {},
        "attachments": {
          "media_keys": [
            "3_2068911963481272320"
          ]
        },
        "author_id": "2047894021457211393",
        "conversation_id": "2068911969076412605",
        "created_at": "2026-06-22T04:20:26.000Z",
        "edit_controls": {
          "editable_until": "2026-06-22T05:20:26.000Z",
          "edits_remaining": 5,
          "is_edit_eligible": true
        },
        "edit_history_tweet_ids": [
          "2068911969076412605"
        ],
        "entities": {
          "urls": [
            {
              "display_url": "pic.x.com/luDeWwJr6v",
              "end": 23,
              "expanded_url": "https://x.com/FanQie_QianQian/status/2068911969076412605/photo/1",
              "media_key": "3_2068911963481272320",
              "start": 0,
              "url": "https://t.co/luDeWwJr6v"
            }
          ]
        },
        "geo": {},
        "id": "2068911969076412605",
        "lang": "zxx",
        "note_tweet": {
          "entities": {}
        },
        "possibly_sensitive": false,
        "public_metrics": {
          "bookmark_count": 1,
          "impression_count": 305,
          "like_count": 9,
          "quote_count": 0,
          "reply_count": 2,
          "retweet_count": 0
        },
        "reply_settings": "everyone",
        "text": "https://t.co/luDeWwJr6v"
      }
    ],
    "users": [
      {
        "created_at": "2026-05-21T11:38:55.000Z",
        "description": "薄巧/炸玉 \n防炸@okokok333444\n查成分回fo",
        "entities": {
          "description": {
            "mentions": [
              {
                "end": 22,
                "start": 9,
                "username": "okokok333444"
              }
            ]
          },
          "url": {
            "urls": [
              {
                "display_url": "ngl.link/boboboqiao",
                "end": 23,
                "expanded_url": "https://ngl.link/boboboqiao",
                "start": 0,
                "url": "https://t.co/Al4Mvhwm7Y"
              }
            ]
          }
        },
        "id": "2057425772198215680",
        "name": "炸玉/二代目",
        "pinned_tweet_id": "2058902425382326345",
        "profile_image_url": "https://pbs.twimg.com/profile_images/2057427270990770176/9ouSJRp6_normal.jpg",
        "protected": false,
        "public_metrics": {
          "followers_count": 655,
          "following_count": 397,
          "like_count": 2434,
          "listed_count": 0,
          "media_count": 78,
          "tweet_count": 1451
        },
        "url": "https://t.co/Al4Mvhwm7Y",
        "username": "boqiaoahm4",
        "verified": false
      },
      {
        "created_at": "2026-04-25T04:22:51.000Z",
        "description": "重生之8.0\n11年 順女 LGBTQ全友好 無門也不接線下\n\n另一個我@_FanQie11_\n\n寶寶 @7q46843886669\n\n好姐姐@OoOooo0518",
        "entities": {
          "description": {
            "mentions": [
              {
                "end": 47,
                "start": 36,
                "username": "_FanQie11_"
              },
              {
                "end": 66,
                "start": 52,
                "username": "7q46843886669"
              },
              {
                "end": 82,
                "start": 71,
                "username": "OoOooo0518"
              }
            ]
          },
          "url": {
            "urls": [
              {
                "display_url": "ngl.link/_tomato._.fanq…",
                "end": 23,
                "expanded_url": "https://ngl.link/_tomato._.fanqie_1",
                "start": 0,
                "url": "https://t.co/JbrJBgq8ZL"
              }
            ]
          }
        },
        "id": "2047894021457211393",
        "name": "番茄操蛋8.0",
        "pinned_tweet_id": "2065786713256141126",
        "profile_image_url": "https://pbs.twimg.com/profile_images/2057140948434649088/mo_BXY2p_normal.jpg",
        "protected": false,
        "public_metrics": {
          "followers_count": 1261,
          "following_count": 109,
          "like_count": 4784,
          "listed_count": 1,
          "media_count": 147,
          "tweet_count": 1816
        },
        "url": "https://t.co/JbrJBgq8ZL",
        "username": "FanQie_QianQian",
        "verified": false
      }
    ]
  }
}